react/__init__.py
react/chatbot.py
react/core.py
react/react.py
gpt_react-0.8.dist-info/METADATA
gpt_react-0.8.dist-info/WHEEL
gpt_react-0.8.dist-info/entry_points.txt
gpt_react-0.8.dist-info/top_level.txt
gpt_react-0.8.dist-info/RECORD
