Metadata-Version: 2.1
Name: gpt-react
Version: 0.8
Requires-Dist: openai
Requires-Dist: httpx
